cgroup_monitor/__init__.py
cgroup_monitor/v1_manager.py
cgroup_monitor/v1_monitor.py
cgroup_monitor/v2_manager.py
cgroup_monitor/v2_monitor.py
cgroup_monitor-1.0.0.dist-info/LICENSE
cgroup_monitor-1.0.0.dist-info/METADATA
cgroup_monitor-1.0.0.dist-info/WHEEL
cgroup_monitor-1.0.0.dist-info/top_level.txt
cgroup_monitor-1.0.0.dist-info/RECORD
