Metadata-Version: 2.2
Name: cgroup-monitor
Version: 1.0.0
Summary: A simple library to monitor CPU and Memory usage only using cgroups. Mainly created to monitor the resources inside the container.
Home-page: https://github.com/veedata/cgroup-monitor
Download-URL: https://github.com/veedata/cgroup-monitor/archive/refs/tags/v1.0.0-stable.tar.gz
Author: Viraj Thakkar
Author-email: vdthakkar111@gmail.com
Project-URL: Code, https://github.com/veedata/cgroup-monitor
Project-URL: Issue tracker, https://github.com/veedata/cgroup-monitor/issues
Project-URL: Documentation, https://cgroup-monitor.readthedocs.io/en/latest
Keywords: cgroup,docker
Classifier: Operating System :: POSIX :: Linux
Classifier: Topic :: System :: Monitoring
Classifier: Development Status :: 5 - Production/Stable
Classifier: Intended Audience :: Developers
Classifier: License :: OSI Approved :: MIT License
Classifier: Programming Language :: Python :: 3.7
Classifier: Programming Language :: Python :: 3.8
Classifier: Programming Language :: Python :: 3.9
Classifier: Programming Language :: Python :: 3.10
Classifier: Programming Language :: Python :: 3.11
License-File: LICENSE
Dynamic: author
Dynamic: author-email
Dynamic: classifier
Dynamic: description
Dynamic: description-content-type
Dynamic: download-url
Dynamic: home-page
Dynamic: keywords
Dynamic: project-url
Dynamic: summary
